Metadata-Version: 1.0
Name: KimPkg
Version: 0.1.1
Summary: Kim Package
Home-page: http://github.com/hgkmail/KimPkg
Author: Kim Huang
Author-email: hgkformap@gmail.com
License: MIT
Platform: UNKNOWN
